{
  "Version": 3,
  "Meta": {
    "Duration": 1.967,
    "Fps": 30.0,
    "Loop": true,
    "AreBeziersRestricted": true,
    "CurveCount": 73,
    "TotalSegmentCount": 107,
    "TotalPointCount": 131,
    "UserDataCount": 1,
    "TotalUserDataSize": 0
  },
  "Curves": [
    {
      "Target": "Parameter",
      "Id": "ParamBreath",
      "Segments": [
        0,
        0,
        0,
        1,
        1,
        0,
        1.967,
        0
      ]
    },
    {
      "Target": "Parameter",
      "Id": "ParamHairFront01",
      "Segments": [
        0,
        0,
        1,
        0.2,
        0,
        0.4,
        1.757,
        0.6,
        1.92,
        1,
        0.744,
        2.038,
        0.889,
        2,
        1.033,
        2,
        0,
        1.967,
        0
      ]
    },
    {
      "Target": "Parameter",
      "Id": "ParamHairFront02",
      "Segments": [
        0,
        0,
        0,
        0.533,
        -2,
        0,
        1.2,
        2.054,
        1,
        1.322,
        2.054,
        1.445,
        2.073,
        1.567,
        2,
        1,
        1.7,
        1.92,
        1.834,
        0,
        1.967,
        0
      ]
    },
    {
      "Target": "Parameter",
      "Id": "ParamHairBackR01",
      "Segments": [
        0,
        0,
        0,
        1,
        -1.04,
        0,
        1.967,
        0
      ]
    },
    {
      "Target": "Parameter",
      "Id": "ParamHairBackR02",
      "Segments": [
        0,
        0,
        0,
        0.5,
        -1.02,
        1,
        0.778,
        -1.02,
        1.055,
        -1.025,
        1.333,
        -0.989,
        1,
        1.544,
        -0.962,
        1.756,
        0,
        1.967,
        0
      ]
    },
    {
      "Target": "Parameter",
      "Id": "ParamHairBackL01",
      "Segments": [
        0,
        0,
        0,
        1,
        -1.006,
        0,
        1.967,
        0
      ]
    },
    {
      "Target": "Parameter",
      "Id": "ParamHairBackL02",
      "Segments": [
        0,
        0,
        1,
        0.167,
        0,
        0.333,
        -0.942,
        0.5,
        -0.98,
        1,
        0.778,
        -1.044,
        1.055,
        -1.041,
        1.333,
        -1.041,
        0,
        1.967,
        0
      ]
    },
    {
      "Target": "Parameter",
      "Id": "ParamBxRibon01",
      "Segments": [
        0,
        0,
        0,
        0.467,
        2.013,
        0,
        1.5,
        -1.048,
        0,
        1.967,
        0
      ]
    },
    {
      "Target": "Parameter",
      "Id": "ParamBxRibon02",
      "Segments": [
        0,
        0,
        0,
        0.333,
        -0.337,
        1,
        0.5,
        -0.337,
        0.666,
        0.193,
        0.833,
        0.98,
        1,
        1,
        1.767,
        1.166,
        2.049,
        1.333,
        2.049,
        0,
        1.967,
        0
      ]
    },
    {
      "Target": "Parameter",
      "Id": "ParamBxSleeveL",
      "Segments": [
        0,
        0,
        0,
        0.667,
        -7,
        0,
        1.4,
        1,
        0,
        1.967,
        0
      ]
    },
    {
      "Target": "Parameter",
      "Id": "ParamBxSleeveRB",
      "Segments": [
        0,
        0,
        0,
        0.9,
        -8,
        0,
        1.967,
        0
      ]
    },
    {
      "Target": "Parameter",
      "Id": "ParamWaist",
      "Segments": [
        0,
        0,
        0,
        0.467,
        3,
        0,
        1.967,
        0
      ]
    },
    {
      "Target": "Parameter",
      "Id": "ParamWaistRibbon01",
      "Segments": [
        0,
        0,
        0,
        0.533,
        -3,
        0,
        1.367,
        4,
        0,
        1.967,
        0
      ]
    },
    {
      "Target": "Parameter",
      "Id": "ParamWaistRibbon02",
      "Segments": [
        0,
        0,
        2,
        0.533,
        0,
        0,
        1.367,
        -4,
        0,
        1.967,
        0
      ]
    },
    {
      "Target": "Parameter",
      "Id": "ParamWaistRibbon03",
      "Segments": [
        0,
        0,
        0,
        0.6,
        -10,
        0,
        1.433,
        2,
        0,
        1.967,
        0
      ]
    },
    {
      "Target": "Parameter",
      "Id": "ParamWaistRibbon04",
      "Segments": [
        0,
        0,
        0,
        0.6,
        -9,
        1,
        0.878,
        -9,
        1.155,
        -8.279,
        1.433,
        -5,
        1,
        1.611,
        -2.901,
        1.789,
        0,
        1.967,
        0
      ]
    },
    {
      "Target": "Parameter",
      "Id": "ParamSkirtX",
      "Segments": [
        0,
        0,
        0,
        0.667,
        -7,
        0,
        1.567,
        3,
        0,
        1.967,
        0
      ]
    },
    {
      "Target": "Parameter",
      "Id": "ParamSkirtY01",
      "Segments": [
        0,
        0,
        0,
        0.7,
        8,
        0,
        1.6,
        -1,
        0,
        1.967,
        0
      ]
    },
    {
      "Target": "Parameter",
      "Id": "ParamAngleX",
      "Segments": [
        0,
        0,
        0,
        1.967,
        0
      ]
    },
    {
      "Target": "Parameter",
      "Id": "ParamAngleY",
      "Segments": [
        0,
        -11,
        0,
        1.967,
        -11
      ]
    },
    {
      "Target": "Parameter",
      "Id": "ParamAngleZ",
      "Segments": [
        0,
        0,
        0,
        1.967,
        0
      ]
    },
    {
      "Target": "Parameter",
      "Id": "ParamEyeLOpen",
      "Segments": [
        0,
        0.9,
        0,
        1.967,
        0.9
      ]
    },
    {
      "Target": "Parameter",
      "Id": "ParamEyeLSmile",
      "Segments": [
        0,
        0,
        0,
        1.967,
        0
      ]
    },
    {
      "Target": "Parameter",
      "Id": "ParamEyeLDeformation",
      "Segments": [
        0,
        0.4,
        0,
        1.967,
        0.4
      ]
    },
    {
      "Target": "Parameter",
      "Id": "ParamEyeROpen",
      "Segments": [
        0,
        0.9,
        0,
        1.967,
        0.9
      ]
    },
    {
      "Target": "Parameter",
      "Id": "ParamEyeRSmile",
      "Segments": [
        0,
        0,
        0,
        1.967,
        0
      ]
    },
    {
      "Target": "Parameter",
      "Id": "ParamEyeRDeformation",
      "Segments": [
        0,
        0.4,
        0,
        1.967,
        0.4
      ]
    },
    {
      "Target": "Parameter",
      "Id": "ParamBxNamida",
      "Segments": [
        0,
        0,
        0,
        1.967,
        0
      ]
    },
    {
      "Target": "Parameter",
      "Id": "ParamNamidaMove",
      "Segments": [
        0,
        0,
        0,
        1.967,
        0
      ]
    },
    {
      "Target": "Parameter",
      "Id": "ParamTearDropR1",
      "Segments": [
        0,
        0,
        0,
        1.967,
        0
      ]
    },
    {
      "Target": "Parameter",
      "Id": "ParamTearDropR2",
      "Segments": [
        0,
        0,
        0,
        1.967,
        0
      ]
    },
    {
      "Target": "Parameter",
      "Id": "ParamTearDropL1",
      "Segments": [
        0,
        0,
        0,
        1.967,
        0
      ]
    },
    {
      "Target": "Parameter",
      "Id": "ParamTearDropL2",
      "Segments": [
        0,
        0,
        0,
        1.967,
        0
      ]
    },
    {
      "Target": "Parameter",
      "Id": "ParamTearDropMove",
      "Segments": [
        0,
        0,
        0,
        1.967,
        0
      ]
    },
    {
      "Target": "Parameter",
      "Id": "ParamTearDropGrainR1",
      "Segments": [
        0,
        0,
        0,
        1.967,
        0
      ]
    },
    {
      "Target": "Parameter",
      "Id": "ParamTearDropGrainR2",
      "Segments": [
        0,
        0,
        0,
        1.967,
        0
      ]
    },
    {
      "Target": "Parameter",
      "Id": "ParamTearDropGrainL1",
      "Segments": [
        0,
        0,
        0,
        1.967,
        0
      ]
    },
    {
      "Target": "Parameter",
      "Id": "ParamTearDropGrainL2",
      "Segments": [
        0,
        0,
        0,
        1.967,
        0
      ]
    },
    {
      "Target": "Parameter",
      "Id": "ParamBxEyeBallScaleX",
      "Segments": [
        0,
        0.3,
        0,
        1.967,
        0.3
      ]
    },
    {
      "Target": "Parameter",
      "Id": "ParamBxEyeBallScaleY",
      "Segments": [
        0,
        -0.5,
        0,
        1.967,
        -0.5
      ]
    },
    {
      "Target": "Parameter",
      "Id": "ParamEyeBallX",
      "Segments": [
        0,
        0,
        0,
        1.967,
        0
      ]
    },
    {
      "Target": "Parameter",
      "Id": "ParamEyeBallY",
      "Segments": [
        0,
        -0.8,
        0,
        1.967,
        -0.8
      ]
    },
    {
      "Target": "Parameter",
      "Id": "ParamBrowRForm",
      "Segments": [
        0,
        -0.6,
        0,
        1.967,
        -0.6
      ]
    },
    {
      "Target": "Parameter",
      "Id": "ParamBrowLForm",
      "Segments": [
        0,
        -0.6,
        0,
        1.967,
        -0.6
      ]
    },
    {
      "Target": "Parameter",
      "Id": "ParamBrowRAngle",
      "Segments": [
        0,
        0,
        0,
        1.967,
        0
      ]
    },
    {
      "Target": "Parameter",
      "Id": "ParamBrowLAngle",
      "Segments": [
        0,
        0,
        0,
        1.967,
        0
      ]
    },
    {
      "Target": "Parameter",
      "Id": "ParamBxBrowRScaleX",
      "Segments": [
        0,
        0.5,
        0,
        1.967,
        0.5
      ]
    },
    {
      "Target": "Parameter",
      "Id": "ParamBxBrowLScaleX",
      "Segments": [
        0,
        0.5,
        0,
        1.967,
        0.5
      ]
    },
    {
      "Target": "Parameter",
      "Id": "ParamBrowRX",
      "Segments": [
        0,
        -0.5,
        0,
        1.967,
        -0.5
      ]
    },
    {
      "Target": "Parameter",
      "Id": "ParamBrowRY",
      "Segments": [
        0,
        -0.6,
        0,
        1.967,
        -0.6
      ]
    },
    {
      "Target": "Parameter",
      "Id": "ParamBrowLX",
      "Segments": [
        0,
        -0.5,
        0,
        1.967,
        -0.5
      ]
    },
    {
      "Target": "Parameter",
      "Id": "ParamBrowLY",
      "Segments": [
        0,
        -0.6,
        0,
        1.967,
        -0.6
      ]
    },
    {
      "Target": "Parameter",
      "Id": "ParamMouthForm",
      "Segments": [
        0,
        -0.3,
        0,
        1.967,
        -0.3
      ]
    },
    {
      "Target": "Parameter",
      "Id": "ParamMouthOpenY",
      "Segments": [
        0,
        0,
        0,
        1.967,
        0
      ]
    },
    {
      "Target": "Parameter",
      "Id": "ParamMouthForm02",
      "Segments": [
        0,
        1,
        0,
        1.967,
        1
      ]
    },
    {
      "Target": "Parameter",
      "Id": "ParamBxMouthY",
      "Segments": [
        0,
        0.2,
        0,
        1.967,
        0.2
      ]
    },
    {
      "Target": "Parameter",
      "Id": "ParamBxMouthScaleX",
      "Segments": [
        0,
        -0.6,
        0,
        1.967,
        -0.6
      ]
    },
    {
      "Target": "Parameter",
      "Id": "ParamBxMouthScaleY",
      "Segments": [
        0,
        0,
        0,
        1.967,
        0
      ]
    },
    {
      "Target": "Parameter",
      "Id": "ParamBodyAngleX",
      "Segments": [
        0,
        0,
        0,
        1.967,
        0
      ]
    },
    {
      "Target": "Parameter",
      "Id": "ParamBodyAngleY",
      "Segments": [
        0,
        0,
        0,
        1.967,
        0
      ]
    },
    {
      "Target": "Parameter",
      "Id": "ParamUpperArmBR",
      "Segments": [
        0,
        -5,
        0,
        1.967,
        -5
      ]
    },
    {
      "Target": "Parameter",
      "Id": "ParamUpperArmBL",
      "Segments": [
        0,
        0,
        0,
        1.967,
        0
      ]
    },
    {
      "Target": "Parameter",
      "Id": "ParamUpperArmLLong",
      "Segments": [
        0,
        8,
        0,
        1.967,
        8
      ]
    },
    {
      "Target": "Parameter",
      "Id": "ParamForeArmR",
      "Segments": [
        0,
        0,
        0,
        1.967,
        0
      ]
    },
    {
      "Target": "Parameter",
      "Id": "ParamForeArmL",
      "Segments": [
        0,
        0,
        0,
        1.967,
        0
      ]
    },
    {
      "Target": "Parameter",
      "Id": "ParamHandR",
      "Segments": [
        0,
        0,
        0,
        1.967,
        0
      ]
    },
    {
      "Target": "Parameter",
      "Id": "ParamBxSodeRAngleZ",
      "Segments": [
        0,
        0,
        0,
        1.967,
        0
      ]
    },
    {
      "Target": "Parameter",
      "Id": "ParamHandL",
      "Segments": [
        0,
        0,
        0,
        1.967,
        0
      ]
    },
    {
      "Target": "Parameter",
      "Id": "Param",
      "Segments": [
        0,
        9,
        0,
        1.967,
        9
      ]
    },
    {
      "Target": "Parameter",
      "Id": "ParamForeArmRC",
      "Segments": [
        0,
        23,
        0,
        1.967,
        23
      ]
    },
    {
      "Target": "Parameter",
      "Id": "ParamBxSodeBRAngleZ",
      "Segments": [
        0,
        15,
        0,
        1.967,
        15
      ]
    },
    {
      "Target": "Parameter",
      "Id": "ParamHandRC",
      "Segments": [
        0,
        -17,
        0,
        1.967,
        -17
      ]
    },
    {
      "Target": "Parameter",
      "Id": "ParamHairBackStretch",
      "Segments": [
        0,
        0,
        0,
        1.967,
        0
      ]
    }
  ],
  "UserData": [
    {
      "Time": 0.0,
      "Value": ""
    }
  ]
}